{
  "dateKey": "2026-07-04",
  "generatedAt": "2026-07-04T04:12:29.974Z",
  "summary": {
    "picks": 10,
    "settled": 2,
    "wins": 0,
    "misses": 2,
    "winRate": 0,
    "excludedFromCalibration": 5,
    "avgClv": 0.005387077537250237,
    "avgBrier": 0.05213767958011415,
    "modelBrier": 0.06150068647483672,
    "marketBrier": 0.047020405572694955,
    "highConfidenceMisses": 0
  },
  "missPatterns": [
    {
      "label": "Unclassified miss",
      "count": 1,
      "avgClv": 0.00900260601753139,
      "avgBrier": 0.05213767958011415
    },
    {
      "label": "Negative CLV miss",
      "count": 1,
      "avgClv": -0.01727173082671804,
      "avgBrier": 0.017060610811126444
    }
  ],
  "recommendations": [
    "No urgent tuning change detected. Keep collecting CLV and settled outcomes."
  ],
  "reviewedPickCount": 10
}
